firebase_crud/__init__.py
firebase_crud/collection.py
firebase_crud-1.0.0.dist-info/LICENSE
firebase_crud-1.0.0.dist-info/METADATA
firebase_crud-1.0.0.dist-info/WHEEL
firebase_crud-1.0.0.dist-info/top_level.txt
firebase_crud-1.0.0.dist-info/RECORD
