Metadata-Version: 2.1
Name: firebase-crud
Version: 1.0.0
Summary: A package to perform crud operations with firebase.
Home-page: https://github.com/jeganathpv/firebase-crud
Author: Jeganath PV
Author-email: jeganathpv@gmail.com
License: UNKNOWN
Project-URL: Bug Tracker, https://github.com/jeganathpv/firebase-crud/issues
Keywords: firebase,crud,database
Platform: UNKNOWN
Classifier: Programming Language :: Python :: 3
Classifier: License :: OSI Approved :: MIT License
Classifier: Operating System :: OS Independent
Requires-Python: >=3.6
License-File: LICENSE
Requires-Dist: firebase-admin
